tokenlog/__init__.py
tokenlog/history.py
tokenlog/tokenizer.py
tokenlog-0.0.3.dist-info/licenses/LICENSE
tokenlog-0.0.3.dist-info/METADATA
tokenlog-0.0.3.dist-info/WHEEL
tokenlog-0.0.3.dist-info/top_level.txt
tokenlog-0.0.3.dist-info/RECORD
