Metadata-Version: 2.4
Name: tokenlog
Version: 0.0.3
Summary: Simplest token log system for your LLM, embedding model calls.
Author-email: vkehfdl1 <vkehfdl1@gmail.com>
License: MIT License
Project-URL: Homepage, https://github.com/vkehfdl1/tokenlog
Keywords: LLM,logging,log,embedding,OpenAI,Huggingface,Token
Classifier: Intended Audience :: Developers
Classifier: Intended Audience :: Information Technology
Classifier: Intended Audience :: Science/Research
Classifier: Programming Language :: Python :: 3.9
Classifier: Programming Language :: Python :: 3.10
Classifier: Programming Language :: Python :: 3.11
Classifier: Programming Language :: Python :: 3.12
Classifier: Topic :: Scientific/Engineering :: Artificial Intelligence
Classifier: Topic :: Software Development :: Libraries
Classifier: Topic :: Software Development :: Libraries :: Python Modules
Requires-Python: >=3.9
License-File: LICENSE
Requires-Dist: jinja2>=3.1.6
Requires-Dist: tiktoken>=0.11.0
Requires-Dist: transformers>=4.56.1
Dynamic: license-file
